Metadata-Version: 1.1
Name: django-remote-forms
Version: 0.0.1
Summary: A platform independent form serializer for Django.
Home-page: http://github.com/wisertoghether/django-remote-forms/
Author: WiserTogether Tech Team
Author-email: tech@wisertogether.com
License: UNKNOWN
Platform: UNKNOWN
Classifier: Development Status :: 1 - Planning
Classifier: Environment :: Web Environment
Classifier: Framework :: Django
Classifier: Intended Audience :: Developers
Classifier: License :: OSI Approved :: MIT License
Classifier: Operating System :: OS Independent
Classifier: Programming Language :: Python
Classifier: Topic :: Utilities
